sciencer/__init__.py
sciencer/core.py
sciencer/models.py
sciencer/policies.py
sciencer/collectors/__init__.py
sciencer/collectors/collect_by_author.py
sciencer/collectors/collect_by_doi.py
sciencer/collectors/collect_by_terms.py
sciencer/collectors/collector.py
sciencer/expanders/__init__.py
sciencer/expanders/expand_by_authors.py
sciencer/expanders/expand_by_citations.py
sciencer/expanders/expand_by_references.py
sciencer/expanders/expander.py
sciencer/filters/__init__.py
sciencer/filters/filter.py
sciencer/filters/filter_by_abstract.py
sciencer/filters/filter_by_field_of_study.py
sciencer/filters/filter_by_year.py
sciencer/providers/__init__.py
sciencer/providers/provider.py
sciencer/providers/semantic_scholar_provider.py
sciencer/utils/__init__.py
sciencer/utils/csv_callback.py
sciencer/utils/history_callback.py
sciencer-0.1.3.dist-info/LICENSE
sciencer-0.1.3.dist-info/METADATA
sciencer-0.1.3.dist-info/WHEEL
sciencer-0.1.3.dist-info/top_level.txt
sciencer-0.1.3.dist-info/RECORD
