Metadata-Version: 2.1
Name: sciencer
Version: 0.1.3
Summary: A smarter way to find new articles
Home-page: https://github.com/SciencerIO/sciencer-toolkit
Author: SciencerIO
Author-email: diogo.rato.11@gmail.com
License: MIT
Platform: UNKNOWN
Classifier: Development Status :: 2 - Pre-Alpha
Classifier: Intended Audience :: Science/Research
Classifier: Intended Audience :: Developers
Classifier: Natural Language :: English
Classifier: Programming Language :: Python :: 3
Classifier: Topic :: Scientific/Engineering
Classifier: Topic :: Utilities
License-File: LICENSE
Requires-Dist: requests
